Activity.txt
Collections.txt
Internals.txt
Porting.txt
README.txt
SQLAlchemy.txt
STM-Observer.txt
_threading_local.py
setup.cfg
setup.py
test_sets.py
test_trellis.py
testreactor.py
Trellis.egg-info/PKG-INFO
Trellis.egg-info/SOURCES.txt
Trellis.egg-info/dependency_links.txt
Trellis.egg-info/namespace_packages.txt
Trellis.egg-info/requires.txt
Trellis.egg-info/top_level.txt
ez_setup/README.txt
ez_setup/__init__.py
peak/__init__.py
peak/events/__init__.py
peak/events/activity.py
peak/events/collections.py
peak/events/sa_support.py
peak/events/stm.py
peak/events/trellis.py