Metadata-Version: 1.0
Name: Trellis
Version: 0.7a1
Summary: A simple "untwisted" approach to event-driven programming
Home-page: http://peak.telecommunity.com/DevCenter/Trellis
Author: Phillip J. Eby
Author-email: peak@eby-sarna.com
License: PSF or ZPL
Platform: UNKNOWN
